Metadata-Version: 2.1
Name: packaging-demo-himanshu
Version: 0.1.0
Summary: My package description
Author-email: Himanshu Kandpal <himanshukandpal0799@gmail.com>
License: MIT
Keywords: one,two
Classifier: Programming Language :: Python :: 3
Requires-Python: >=3.7
Requires-Dist: numpy
Requires-Dist: fastapi
Provides-Extra: dev
Requires-Dist: packaging-demo-himanshu[release,static-code-qa,test] ; extra == 'dev'
Provides-Extra: release
Requires-Dist: build ; extra == 'release'
Requires-Dist: twine ; extra == 'release'
Requires-Dist: pre-commit ; extra == 'release'
Provides-Extra: static-code-qa
Requires-Dist: pre-commit ; extra == 'static-code-qa'
Provides-Extra: test
Requires-Dist: pytest ; extra == 'test'
Requires-Dist: pytest-cov ; extra == 'test'
